wp2genes/__init__.py
wp2genes/wp2genes.py
wikipathway2genes-0.0.5.dist-info/METADATA
wikipathway2genes-0.0.5.dist-info/WHEEL
wikipathway2genes-0.0.5.dist-info/entry_points.txt
wikipathway2genes-0.0.5.dist-info/top_level.txt
wikipathway2genes-0.0.5.dist-info/RECORD
