Metadata-Version: 2.1
Name: wikipathway2genes
Version: 0.0.5
Summary: A package to convert WikiPathways IDs to genes
Author: Pr (France) Dr. rer. nat. Vijay K. ULAGANATHAN
Author-email: 
Requires-Dist: argparse
Requires-Dist: pywikipathways
